{
    "nodes":[
        {"id":1,"title":"BIOL 107","x":874.427001953125,"y":410.7142333984375},
        {"id":3,"title":"BIOL 108","x":584.03125,"y":416.1929931640625},
        {"id":4,"title":"CHEM 101","x":1120.9879150390625,"y":415.3465881347656},
        {"id":5,"title":"CHEM 102","x":1476.0183715820312,"y":294.79825592041016},
        {"id":6,"title":"STAT 151","x":1873.1905517578125,"y":384.5248107910156},
        {"id":7,"title":"MATH 125","x":1819.0906982421875,"y":199.79367065429688},
        {"id":8,"title":"MATH 134","x":1977.804443359375,"y":274.86785888671875},
        {"id":9,"title":"BIOL 208","x":599.8653564453125,"y":92.91354370117188},
        {"id":10,"title":"BIOL 207","x":781.9574584960938,"y":57.28683090209961},
        {"id":11,"title":"GENET 270","x":792.5134887695312,"y":-172.3075408935547},
        {"id":12,"title":"BIOL 201","x":936.0741577148438,"y":51.74306845664978},
        {"id":13,"title":"CELL 201","x":1065.1539306640625,"y":45.18700551986694},
        {"id":14,"title":"MICRB 265","x":1058.9296875,"y":-171.46115112304688},
        {"id":15,"title":"CHEM 261","x":1344.0677490234375,"y":48.050275802612305},
        {"id":17,"title":"BIOCH 330","x":1792.81689453125,"y":-369.1920471191406},
        {"id":18,"title":"BIOCH 200","x":1290.9525146484375,"y":-192.37640380859375},
        {"id":19,"title":"CHEM 263","x":1436.6160888671875,"y":-161.22431182861328},
        {"id":20,"title":"IMIN 200","x":1522.9461669921875,"y":-357.00433349609375}
    ],  
    "links":[
        {"source":3,"target":9},
        {"source":1,"target":10},
        {"source":1,"target":12},
        {"source":1,"target":13},
        {"source":10,"target":11},
        {"source":1,"target":14},
        {"source":4,"target":12},
        {"source":15,"target":13},
        {"source":4,"target":15},
        {"source":5,"target":17},
        {"source":15,"target":14},
        {"source":15,"target":18},
        {"source":15,"target":19},
        {"source":18,"target":20},
        {"source":14,"target":20},
        {"source":19,"target":17},
        {"source":18,"target":17}
    ]
}